README.txt
setup.py
collective/__init__.py
collective.collage.plonetruegallery.egg-info/PKG-INFO
collective.collage.plonetruegallery.egg-info/SOURCES.txt
collective.collage.plonetruegallery.egg-info/dependency_links.txt
collective.collage.plonetruegallery.egg-info/entry_points.txt
collective.collage.plonetruegallery.egg-info/namespace_packages.txt
collective.collage.plonetruegallery.egg-info/not-zip-safe
collective.collage.plonetruegallery.egg-info/requires.txt
collective.collage.plonetruegallery.egg-info/top_level.txt
collective/collage/__init__.py
collective/collage/plonetruegallery/__init__.py
collective/collage/plonetruegallery/configure.zcml
collective/collage/plonetruegallery/gallery.pt
collective/collage/plonetruegallery/views.py
collective/collage/plonetruegallery/patches/__init__.py
collective/collage/plonetruegallery/patches/plonetruegallery_browser_util.py
docs/HISTORY.txt