Metadata-Version: 1.0
Name: collective.collage.plonetruegallery
Version: 1.0b1
Summary: Show a PloneTrueGallery slideshow in a Collage
Home-page: http://plone.org/products/collective.collage.plonetruegallery
Author: Kees Hink
Author-email: hink@gw20e.com
License: GPL
Platform: UNKNOWN
Classifier: Programming Language :: Python
